src/__init__.py
src/gitlab_docs.py
src/modules/__init__.py
src/modules/command_reference.py
src/modules/common.py
src/modules/doc_controller.py
src/modules/logging.py
src/modules/yaml_md_table.py
src/properties/__init__.py
src/properties/extract_job_attribute.py
src/properties/includes.py
src/properties/inputs.py
src/properties/jobs.py
src/properties/variables.py
src/properties/workflows.py
gitlab_docs-1.0.5.dist-info/METADATA
gitlab_docs-1.0.5.dist-info/WHEEL
gitlab_docs-1.0.5.dist-info/entry_points.txt
gitlab_docs-1.0.5.dist-info/licenses/LICENSE
gitlab_docs-1.0.5.dist-info/RECORD
