Metadata-Version: 2.4
Name: gitlab-docs
Version: 1.0.5
Summary: A tool that automatically generates gitlab documentation from yaml files
License-File: LICENSE
Author: Charlie Smith
Author-email: me@charlieasmith.co.uk
Requires-Python: >=3.12.11,<4.0.0
Classifier: Programming Language :: Python :: 3
Classifier: Programming Language :: Python :: 3.13
Classifier: Programming Language :: Python :: 3.14
Requires-Dist: click (<=7.1.2)
Requires-Dist: jq (>=1.8.0,<2.0.0)
Requires-Dist: loguru (==0.7.0)
Requires-Dist: markdown-analysis
Requires-Dist: oyaml
Requires-Dist: prettytable
Requires-Dist: pytablewriter (>=1.2.0,<1.3.0)
Requires-Dist: pyyaml (>=6.0.2,<7.0.0)
Requires-Dist: semver (>=3.0.2,<4.0.0)
Requires-Dist: setuptools
Requires-Dist: typer (>=0.10.0,<0.11.0)
Project-URL: Documentation, https://pypi.org/manage/project/gitlab-docs
Project-URL: Gitlab, https://gitlab.com/charlieasmith/gitlab-docs
Project-URL: Home Page, https://pypi.org/manage/project/gitlab-docs
Project-URL: Repository, https://gitlab.com/charlieasmith/gitlab-docs
